sparql_dataframe/__init__.py
sparql_dataframe/sparql_dataframe.py
sparql_dataframe-0.4.dist-info/LICENSE
sparql_dataframe-0.4.dist-info/METADATA
sparql_dataframe-0.4.dist-info/WHEEL
sparql_dataframe-0.4.dist-info/top_level.txt
sparql_dataframe-0.4.dist-info/RECORD
