Metadata-Version: 2.1
Name: sparql-dataframe
Version: 0.4
Summary: Convert SPARQL results to Pandas dataframes
Home-page: https://github.com/lawlesst/sparql-dataframe
Author: Ted Lawless
Author-email: lawlesst@gmail.com
License: MIT
Platform: UNKNOWN
Requires-Dist: pandas (>=0.22.0)
Requires-Dist: SPARQLWrapper (>=1.8.1)
